gubchat/__init__.py
gubchat/database.py
gubchat/gubchatapp.py
gubchat/helix.py
gubchat/main.py
gubchat/twitch_websocket.py
gubchat/user_auth.py
gubchat/alembic/env.py
gubchat-0.1.4.dist-info/LICENSE
gubchat-0.1.4.dist-info/METADATA
gubchat-0.1.4.dist-info/WHEEL
gubchat-0.1.4.dist-info/entry_points.txt
gubchat-0.1.4.dist-info/top_level.txt
gubchat-0.1.4.dist-info/RECORD
